abs_nosql_integration_core/__init__.py
abs_nosql_integration_core/model/__init__.py
abs_nosql_integration_core/model/integration_model.py
abs_nosql_integration_core/model/subscription_model.py
abs_nosql_integration_core/repository/__init__.py
abs_nosql_integration_core/repository/integration_repository.py
abs_nosql_integration_core/repository/subscription_repository.py
abs_nosql_integration_core/schema/__init__.py
abs_nosql_integration_core/schema/integration_schema.py
abs_nosql_integration_core/schema/subscription_schema.py
abs_nosql_integration_core/service/__init__.py
abs_nosql_integration_core/service/nosql_integration_service.py
abs_nosql_integration_core/service/nosql_subscription_service.py
abs_nosql_integration_core/service/provider_services/__init__.py
abs_nosql_integration_core/service/provider_services/calendar_integration_service.py
abs_nosql_integration_core/service/provider_services/docusign_integration_service.py
abs_nosql_integration_core/service/provider_services/google_integration_service.py
abs_nosql_integration_core/service/provider_services/outlook_integration_service.py
abs_nosql_integration_core/service/provider_services/sharepoint_integration_service.py
abs_nosql_integration_core/utils/__init__.py
abs_nosql_integration_core/utils/provider_service_factory.py
abs_nosql_integration_core-0.3.3.dist-info/METADATA
abs_nosql_integration_core-0.3.3.dist-info/WHEEL
abs_nosql_integration_core-0.3.3.dist-info/RECORD
