Metadata-Version: 2.3
Name: abs-nosql-integration-core
Version: 0.3.3
Summary: Core utilities for building OAuth-based integrations in FastAPI applications with use of NoSql db
License: MIT
Author: AutoBridgeSystems
Author-email: info@autobridgesystems.com
Requires-Python: >=3.11,<4.0
Classifier: License :: OSI Approved :: MIT License
Classifier: Programming Language :: Python :: 3
Classifier: Programming Language :: Python :: 3.11
Classifier: Programming Language :: Python :: 3.12
Classifier: Programming Language :: Python :: 3.13
Requires-Dist: abs-exception-core (>=0.2.0,<0.3.0)
Requires-Dist: abs-integration-core (>=0.2.3,<0.3.0)
Requires-Dist: abs-nosql-repository-core (>=0.11.5,<0.12.0)
Requires-Dist: fastapi (>=0.95.0,<2.0.0)
Requires-Dist: httpx (>=0.28.1,<0.29.0)
Requires-Dist: pydantic (>=2.0.0,<3.0.0)
